{"field":["193","2","213","239","2390","2483","251","2628","52","84","87","99"],"bracket":{"seeds":[{"team_id":"84","team_name":"Indiana Hoosiers","seed":1,"fpi":39.05},{"team_id":"87","team_name":"Notre Dame Fighting Irish","seed":2,"fpi":38.47},{"team_id":"99","team_name":"LSU Tigers","seed":3,"fpi":34.2},{"team_id":"213","team_name":"Penn State Nittany Lions","seed":4,"fpi":31.53},{"team_id":"2483","team_name":"Oregon Ducks","seed":5,"fpi":26.37},{"team_id":"2390","team_name":"Miami Hurricanes","seed":6,"fpi":25.08},{"team_id":"2","team_name":"Auburn Tigers","seed":7,"fpi":23.79},{"team_id":"2628","team_name":"TCU Horned Frogs","seed":8,"fpi":23.45},{"team_id":"52","team_name":"Florida State Seminoles","seed":9,"fpi":20.48},{"team_id":"251","team_name":"Texas Longhorns","seed":10,"fpi":19.82},{"team_id":"193","team_name":"Miami (OH) RedHawks","seed":11,"fpi":12.6},{"team_id":"239","team_name":"Baylor Bears","seed":12,"fpi":6.42}],"r1":[[5,12],[6,11],[7,10],[8,9]],"title_odds_by_team_id":{"84":32.36,"87":29.88,"99":19.03,"213":11.54,"2483":3.08,"2390":1.98,"2":0.84,"2628":0.75,"52":0.28,"251":0.23,"193":0.03,"239":0.0}},"conf_champions":{"ACC":"2390","American":"2426","Big 12":"2628","Big Ten":"213","CUSA":"2229","MAC":"2649","Mountain West":"167","Pac-12":"68","SEC":"2","Sun Belt":"256"},"conf_finalists":{"ACC":["2390","183"],"American":["2426","242"],"Big 12":["252","2628"],"Big Ten":["84","213"],"CUSA":["2229","98"],"MAC":["193","2649"],"Mountain West":["2449","167"],"Pac-12":["68","326"],"SEC":["99","2"],"Sun Belt":["2433","256"]}}