{"field":["130","213","235","2483","2628","2641","333","61","84","87","97","99"],"bracket":{"seeds":[{"team_id":"84","team_name":"Indiana Hoosiers","seed":1,"fpi":36.41},{"team_id":"2483","team_name":"Oregon Ducks","seed":2,"fpi":32.0},{"team_id":"130","team_name":"Michigan Wolverines","seed":3,"fpi":31.61},{"team_id":"99","team_name":"LSU Tigers","seed":4,"fpi":26.57},{"team_id":"61","team_name":"Georgia Bulldogs","seed":5,"fpi":24.4},{"team_id":"333","team_name":"Alabama Crimson Tide","seed":6,"fpi":21.45},{"team_id":"87","team_name":"Notre Dame Fighting Irish","seed":7,"fpi":20.93},{"team_id":"97","team_name":"Louisville Cardinals","seed":8,"fpi":17.16},{"team_id":"213","team_name":"Penn State Nittany Lions","seed":9,"fpi":16.74},{"team_id":"2628","team_name":"TCU Horned Frogs","seed":10,"fpi":16.63},{"team_id":"2641","team_name":"Texas Tech Red Raiders","seed":11,"fpi":14.2},{"team_id":"235","team_name":"Memphis Tigers","seed":12,"fpi":4.9}],"r1":[[5,12],[6,11],[7,10],[8,9]],"title_odds_by_team_id":{"84":39.71,"2483":20.45,"130":22.47,"99":8.85,"61":4.46,"333":1.71,"87":1.13,"97":0.4,"213":0.35,"2628":0.29,"2641":0.16,"235":0.01}},"conf_champions":{"ACC":"97","American":"235","Big 12":"2641","Big Ten":"84","CUSA":"2229","MAC":"195","Mountain West":"167","Pac-12":"326","SEC":"333","Sun Belt":"295"},"conf_finalists":{"ACC":["97","2390"],"American":["235","2655"],"Big 12":["2641","2305"],"Big Ten":["84","2483"],"CUSA":["2229","2623"],"MAC":["2649","195"],"Mountain West":["167","2449"],"Pac-12":["326","68"],"SEC":["99","333"],"Sun Belt":["295","324"]}}