{"field":["130","194","213","221","2306","245","254","2633","333","58","87","97"],"bracket":{"seeds":[{"team_id":"194","team_name":"Ohio State Buckeyes","seed":1,"fpi":36.0},{"team_id":"130","team_name":"Michigan Wolverines","seed":2,"fpi":33.27},{"team_id":"245","team_name":"Texas A&M Aggies","seed":3,"fpi":30.93},{"team_id":"2633","team_name":"Tennessee Volunteers","seed":4,"fpi":27.97},{"team_id":"97","team_name":"Louisville Cardinals","seed":5,"fpi":27.83},{"team_id":"333","team_name":"Alabama Crimson Tide","seed":6,"fpi":27.53},{"team_id":"221","team_name":"Pittsburgh Panthers","seed":7,"fpi":25.62},{"team_id":"87","team_name":"Notre Dame Fighting Irish","seed":8,"fpi":24.09},{"team_id":"213","team_name":"Penn State Nittany Lions","seed":9,"fpi":24.04},{"team_id":"2306","team_name":"Kansas State Wildcats","seed":10,"fpi":19.21},{"team_id":"58","team_name":"South Florida Bulls","seed":11,"fpi":13.22},{"team_id":"254","team_name":"Utah Utes","seed":12,"fpi":9.82}],"r1":[[5,12],[6,11],[7,10],[8,9]],"title_odds_by_team_id":{"194":31.98,"130":21.91,"245":16.48,"2633":9.73,"97":7.36,"333":6.13,"221":2.85,"87":1.55,"213":1.52,"2306":0.39,"58":0.07,"254":0.02}},"conf_champions":{"ACC":"97","American":"58","Big 12":"2306","Big Ten":"194","CUSA":"166","MAC":"195","Mountain West":"2005","Pac-12":"68","SEC":"245","Sun Belt":"256"},"conf_finalists":{"ACC":["221","97"],"American":["58","151"],"Big 12":["2306","254"],"Big Ten":["130","194"],"CUSA":["2335","166"],"MAC":["195","2649"],"Mountain West":["2005","2439"],"Pac-12":["68","278"],"SEC":["245","2633"],"Sun Belt":["256","295"]}}