{"field":["145","2","2294","2483","258","2623","2633","2641","275","356","66","87"],"bracket":{"seeds":[{"team_id":"145","team_name":"Ole Miss Rebels","seed":1,"fpi":40.0},{"team_id":"66","team_name":"Iowa State Cyclones","seed":2,"fpi":27.75},{"team_id":"87","team_name":"Notre Dame Fighting Irish","seed":3,"fpi":26.71},{"team_id":"2294","team_name":"Iowa Hawkeyes","seed":4,"fpi":25.28},{"team_id":"2633","team_name":"Tennessee Volunteers","seed":5,"fpi":21.48},{"team_id":"2","team_name":"Auburn Tigers","seed":6,"fpi":20.49},{"team_id":"2483","team_name":"Oregon Ducks","seed":7,"fpi":19.64},{"team_id":"258","team_name":"Virginia Cavaliers","seed":8,"fpi":17.39},{"team_id":"2641","team_name":"Texas Tech Red Raiders","seed":9,"fpi":13.39},{"team_id":"356","team_name":"Illinois Fighting Illini","seed":10,"fpi":3.84},{"team_id":"275","team_name":"Wisconsin Badgers","seed":11,"fpi":-2.34},{"team_id":"2623","team_name":"Missouri State Bears","seed":12,"fpi":-11.88}],"r1":[[5,12],[6,11],[7,10],[8,9]],"title_odds_by_team_id":{"145":60.59,"66":11.45,"87":11.37,"2294":8.36,"2633":3.42,"2":2.55,"2483":1.5,"258":0.59,"2641":0.16,"356":0.01,"275":0.0,"2623":0.0}},"conf_champions":{"ACC":"258","American":"2636","Big 12":"66","Big Ten":"2294","CUSA":"338","MAC":"193","Mountain West":"2439","Pac-12":"265","SEC":"145","Sun Belt":"295"},"conf_finalists":{"ACC":["2390","258"],"American":["2636","349"],"Big 12":["66","12"],"Big Ten":["2483","2294"],"CUSA":["2335","338"],"MAC":["193","195"],"Mountain West":["2449","2439"],"Pac-12":["326","265"],"SEC":["61","145"],"Sun Belt":["2653","295"]}}