{"field":["130","2348","2390","245","2483","251","2567","2628","2641","30","333","97"],"bracket":{"seeds":[{"team_id":"2641","team_name":"Texas Tech Red Raiders","seed":1,"fpi":36.34},{"team_id":"2483","team_name":"Oregon Ducks","seed":2,"fpi":32.66},{"team_id":"251","team_name":"Texas Longhorns","seed":3,"fpi":29.52},{"team_id":"130","team_name":"Michigan Wolverines","seed":4,"fpi":22.73},{"team_id":"2390","team_name":"Miami Hurricanes","seed":5,"fpi":21.36},{"team_id":"2567","team_name":"SMU Mustangs","seed":6,"fpi":13.6},{"team_id":"97","team_name":"Louisville Cardinals","seed":7,"fpi":13.23},{"team_id":"245","team_name":"Texas A&M Aggies","seed":8,"fpi":10.43},{"team_id":"30","team_name":"USC Trojans","seed":9,"fpi":8.39},{"team_id":"333","team_name":"Alabama Crimson Tide","seed":10,"fpi":8.28},{"team_id":"2628","team_name":"TCU Horned Frogs","seed":11,"fpi":6.48},{"team_id":"2348","team_name":"Louisiana Tech Bulldogs","seed":12,"fpi":-8.42}],"r1":[[5,12],[6,11],[7,10],[8,9]],"title_odds_by_team_id":{"2641":42.65,"2483":25.64,"251":22.08,"130":5.28,"2390":3.53,"2567":0.4,"97":0.22,"245":0.1,"30":0.05,"333":0.04,"2628":0.03,"2348":0.0}},"conf_champions":{"ACC":"2567","American":"2426","Big 12":"2641","Big Ten":"2483","CUSA":"2335","MAC":"16","Mountain West":"23","Pac-12":"68","SEC":"251","Sun Belt":"2653"},"conf_finalists":{"ACC":["2567","258"],"American":["151","2426"],"Big 12":["2641","254"],"Big Ten":["194","2483"],"CUSA":["98","2335"],"MAC":["16","2050"],"Mountain West":["23","2449"],"Pac-12":["68","204"],"SEC":["99","251"],"Sun Belt":["2026","2653"]}}