{"field":["130","2","221","2390","2449","2483","2567","2641","30","333","66","87"],"bracket":{"seeds":[{"team_id":"2390","team_name":"Miami Hurricanes","seed":1,"fpi":35.61},{"team_id":"87","team_name":"Notre Dame Fighting Irish","seed":2,"fpi":24.97},{"team_id":"2483","team_name":"Oregon Ducks","seed":3,"fpi":21.41},{"team_id":"2641","team_name":"Texas Tech Red Raiders","seed":4,"fpi":19.15},{"team_id":"30","team_name":"USC Trojans","seed":5,"fpi":19.02},{"team_id":"66","team_name":"Iowa State Cyclones","seed":6,"fpi":18.75},{"team_id":"2","team_name":"Auburn Tigers","seed":7,"fpi":16.43},{"team_id":"130","team_name":"Michigan Wolverines","seed":8,"fpi":16.39},{"team_id":"2567","team_name":"SMU Mustangs","seed":9,"fpi":15.68},{"team_id":"221","team_name":"Pittsburgh Panthers","seed":10,"fpi":5.05},{"team_id":"333","team_name":"Alabama Crimson Tide","seed":11,"fpi":0.27},{"team_id":"2449","team_name":"North Dakota State Bison","seed":12,"fpi":-12.78}],"r1":[[5,12],[6,11],[7,10],[8,9]],"title_odds_by_team_id":{"2390":56.53,"87":14.58,"2483":9.63,"2641":6.01,"30":5.41,"66":4.36,"2":1.65,"130":0.98,"2567":0.79,"221":0.04,"333":0.01,"2449":0.0}},"conf_champions":{"ACC":"2390","American":"249","Big 12":"66","Big Ten":"2483","CUSA":"2229","MAC":"193","Mountain West":"2440","Pac-12":"21","SEC":"2","Sun Belt":"295"},"conf_finalists":{"ACC":["2390","2567"],"American":["249","58"],"Big 12":["38","66"],"Big Ten":["84","2483"],"CUSA":["2229","2393"],"MAC":["193","195"],"Mountain West":["2439","2440"],"Pac-12":["278","21"],"SEC":["2","142"],"Sun Belt":["324","295"]}}