{"field":["130","145","2294","235","2390","2483","2567","2641","59","84","87","99"],"bracket":{"seeds":[{"team_id":"87","team_name":"Notre Dame Fighting Irish","seed":1,"fpi":39.46},{"team_id":"2641","team_name":"Texas Tech Red Raiders","seed":2,"fpi":31.96},{"team_id":"130","team_name":"Michigan Wolverines","seed":3,"fpi":28.98},{"team_id":"2390","team_name":"Miami Hurricanes","seed":4,"fpi":26.58},{"team_id":"59","team_name":"Georgia Tech Yellow Jackets","seed":5,"fpi":20.46},{"team_id":"145","team_name":"Ole Miss Rebels","seed":6,"fpi":19.79},{"team_id":"2483","team_name":"Oregon Ducks","seed":7,"fpi":15.72},{"team_id":"84","team_name":"Indiana Hoosiers","seed":8,"fpi":15.61},{"team_id":"2294","team_name":"Iowa Hawkeyes","seed":9,"fpi":14.21},{"team_id":"99","team_name":"LSU Tigers","seed":10,"fpi":13.67},{"team_id":"2567","team_name":"SMU Mustangs","seed":11,"fpi":4.73},{"team_id":"235","team_name":"Memphis Tigers","seed":12,"fpi":-1.89}],"r1":[[5,12],[6,11],[7,10],[8,9]],"title_odds_by_team_id":{"87":51.58,"2641":19.44,"130":15.01,"2390":9.51,"59":2.06,"145":1.55,"2483":0.28,"84":0.26,"2294":0.16,"99":0.14,"2567":0.01,"235":0.0}},"conf_champions":{"ACC":"59","American":"2655","Big 12":"2641","Big Ten":"130","CUSA":"2335","MAC":"193","Mountain West":"2449","Pac-12":"278","SEC":"145","Sun Belt":"290"},"conf_finalists":{"ACC":["2390","59"],"American":["2655","249"],"Big 12":["2641","248"],"Big Ten":["264","130"],"CUSA":["2335","166"],"MAC":["193","2006"],"Mountain West":["2449","2439"],"Pac-12":["278","21"],"SEC":["145","333"],"Sun Belt":["256","290"]}}