{"field":["130","2294","2390","2483","251","264","2641","333","356","57","68","87"],"bracket":{"seeds":[{"team_id":"2390","team_name":"Miami Hurricanes","seed":1,"fpi":29.1},{"team_id":"2294","team_name":"Iowa Hawkeyes","seed":2,"fpi":28.3},{"team_id":"264","team_name":"Washington Huskies","seed":3,"fpi":28.05},{"team_id":"2483","team_name":"Oregon Ducks","seed":4,"fpi":24.03},{"team_id":"130","team_name":"Michigan Wolverines","seed":5,"fpi":23.84},{"team_id":"251","team_name":"Texas Longhorns","seed":6,"fpi":23.79},{"team_id":"87","team_name":"Notre Dame Fighting Irish","seed":7,"fpi":23.66},{"team_id":"57","team_name":"Florida Gators","seed":8,"fpi":23.66},{"team_id":"333","team_name":"Alabama Crimson Tide","seed":9,"fpi":22.36},{"team_id":"356","team_name":"Illinois Fighting Illini","seed":10,"fpi":18.04},{"team_id":"68","team_name":"Boise State Broncos","seed":11,"fpi":15.27},{"team_id":"2641","team_name":"Texas Tech Red Raiders","seed":12,"fpi":11.21}],"r1":[[5,12],[6,11],[7,10],[8,9]],"title_odds_by_team_id":{"2390":21.81,"2294":20.06,"264":21.12,"2483":10.85,"130":7.24,"251":5.93,"87":4.74,"57":3.94,"333":2.75,"356":0.93,"68":0.48,"2641":0.16}},"conf_champions":{"ACC":"2390","American":"235","Big 12":"2641","Big Ten":"264","CUSA":"338","MAC":"2050","Mountain West":"2449","Pac-12":"68","SEC":"57","Sun Belt":"256"},"conf_finalists":{"ACC":["221","2390"],"American":["151","235"],"Big 12":["2306","2641"],"Big Ten":["264","2294"],"CUSA":["338","2229"],"MAC":["2050","2084"],"Mountain West":["2449","62"],"Pac-12":["68","278"],"SEC":["57","333"],"Sun Belt":["2026","256"]}}