{"field":["130","194","201","213","2390","2449","2483","251","26","2641","84","87"],"bracket":{"seeds":[{"team_id":"87","team_name":"Notre Dame Fighting Irish","seed":1,"fpi":40.0},{"team_id":"251","team_name":"Texas Longhorns","seed":2,"fpi":38.58},{"team_id":"194","team_name":"Ohio State Buckeyes","seed":3,"fpi":37.23},{"team_id":"84","team_name":"Indiana Hoosiers","seed":4,"fpi":34.33},{"team_id":"2641","team_name":"Texas Tech Red Raiders","seed":5,"fpi":32.53},{"team_id":"2483","team_name":"Oregon Ducks","seed":6,"fpi":24.55},{"team_id":"130","team_name":"Michigan Wolverines","seed":7,"fpi":24.52},{"team_id":"2390","team_name":"Miami Hurricanes","seed":8,"fpi":23.15},{"team_id":"201","team_name":"Oklahoma Sooners","seed":9,"fpi":23.05},{"team_id":"213","team_name":"Penn State Nittany Lions","seed":10,"fpi":15.72},{"team_id":"26","team_name":"UCLA Bruins","seed":11,"fpi":9.8},{"team_id":"2449","team_name":"North Dakota State Bison","seed":12,"fpi":-4.48}],"r1":[[5,12],[6,11],[7,10],[8,9]],"title_odds_by_team_id":{"87":30.82,"251":25.6,"194":22.64,"84":10.92,"2641":7.17,"2483":1.09,"130":0.86,"2390":0.44,"201":0.42,"213":0.04,"26":0.01,"2449":0.0}},"conf_champions":{"ACC":"2390","American":"2636","Big 12":"2641","Big Ten":"194","CUSA":"2335","MAC":"193","Mountain West":"2439","Pac-12":"204","SEC":"251","Sun Belt":"256"},"conf_finalists":{"ACC":["2390","25"],"American":["349","2636"],"Big 12":["2641","2306"],"Big Ten":["194","84"],"CUSA":["2335","2393"],"MAC":["189","193"],"Mountain West":["2439","167"],"Pac-12":["204","265"],"SEC":["145","251"],"Sun Belt":["256","2653"]}}