{"field":["142","145","158","213","228","2306","2483","2567","265","333","84","87"],"bracket":{"seeds":[{"team_id":"84","team_name":"Indiana Hoosiers","seed":1,"fpi":40.0,"wins":13,"losses":0,"record":"13-0"},{"team_id":"87","team_name":"Notre Dame Fighting Irish","seed":2,"fpi":36.09,"wins":12,"losses":0,"record":"12-0"},{"team_id":"145","team_name":"Ole Miss Rebels","seed":3,"fpi":23.67,"wins":10,"losses":3,"record":"10-3"},{"team_id":"213","team_name":"Penn State Nittany Lions","seed":4,"fpi":22.95,"wins":11,"losses":2,"record":"11-2"},{"team_id":"228","team_name":"Clemson Tigers","seed":5,"fpi":21.53,"wins":11,"losses":2,"record":"11-2"},{"team_id":"2567","team_name":"SMU Mustangs","seed":6,"fpi":20.53,"wins":11,"losses":2,"record":"11-2"},{"team_id":"2483","team_name":"Oregon Ducks","seed":7,"fpi":19.53,"wins":10,"losses":2,"record":"10-2"},{"team_id":"333","team_name":"Alabama Crimson Tide","seed":8,"fpi":14.84,"wins":10,"losses":3,"record":"10-3"},{"team_id":"142","team_name":"Missouri Tigers","seed":9,"fpi":13.15,"wins":9,"losses":3,"record":"9-3"},{"team_id":"2306","team_name":"Kansas State Wildcats","seed":10,"fpi":12.86,"wins":12,"losses":1,"record":"12-1"},{"team_id":"265","team_name":"Washington State Cougars","seed":11,"fpi":11.03,"wins":10,"losses":3,"record":"10-3"},{"team_id":"158","team_name":"Nebraska Cornhuskers","seed":12,"fpi":8.42,"wins":10,"losses":2,"record":"10-2"}],"r1":[[5,12],[6,11],[7,10],[8,9]],"title_odds_by_team_id":{"84":50.56,"87":30.15,"145":6.9,"213":5.89,"228":3.03,"2567":2.22,"2483":0.69,"333":0.2,"142":0.11,"2306":0.08,"265":0.11,"158":0.05}},"conf_champions":{"ACC":"2567","American":"249","Big 12":"2306","Big Ten":"84","CUSA":"2229","MAC":"2711","Mountain West":"2751","Pac-12":"265","SEC":"145","Sun Belt":"295"},"conf_finalists":{"ACC":["2567","228"],"American":["249","349"],"Big 12":["2641","2306"],"Big Ten":["84","213"],"CUSA":["98","2229"],"MAC":["2711","16"],"Mountain West":["2751","2439"],"Pac-12":["68","265"],"SEC":["333","145"],"Sun Belt":["295","2032"]}}