{"field":["2","213","2294","238","2483","251","278","36","61","87","9","97"],"bracket":{"seeds":[{"team_id":"2483","team_name":"Oregon Ducks","seed":1,"fpi":39.24},{"team_id":"87","team_name":"Notre Dame Fighting Irish","seed":2,"fpi":38.26},{"team_id":"61","team_name":"Georgia Bulldogs","seed":3,"fpi":30.32},{"team_id":"2294","team_name":"Iowa Hawkeyes","seed":4,"fpi":25.23},{"team_id":"2","team_name":"Auburn Tigers","seed":5,"fpi":24.62},{"team_id":"251","team_name":"Texas Longhorns","seed":6,"fpi":24.24},{"team_id":"238","team_name":"Vanderbilt Commodores","seed":7,"fpi":22.61},{"team_id":"213","team_name":"Penn State Nittany Lions","seed":8,"fpi":22.35},{"team_id":"36","team_name":"Colorado State Rams","seed":9,"fpi":17.33},{"team_id":"9","team_name":"Arizona State Sun Devils","seed":10,"fpi":16.18},{"team_id":"97","team_name":"Louisville Cardinals","seed":11,"fpi":10.09},{"team_id":"278","team_name":"Fresno State Bulldogs","seed":12,"fpi":-0.99}],"r1":[[5,12],[6,11],[7,10],[8,9]],"title_odds_by_team_id":{"2483":38.0,"87":33.54,"61":14.18,"2294":5.29,"2":4.03,"251":2.89,"238":0.93,"213":0.83,"36":0.16,"9":0.11,"97":0.03,"278":0.0}},"conf_champions":{"ACC":"97","American":"2636","Big 12":"9","Big Ten":"2483","CUSA":"2335","MAC":"2649","Mountain West":"2449","Pac-12":"36","SEC":"61","Sun Belt":"2026"},"conf_finalists":{"ACC":["97","228"],"American":["2636","58"],"Big 12":["9","2132"],"Big Ten":["2483","2294"],"CUSA":["2623","2335"],"MAC":["2649","2711"],"Mountain West":["2449","2459"],"Pac-12":["278","36"],"SEC":["61","99"],"Sun Belt":["256","2026"]}}