{"field":["103","189","194","2","201","2116","213","2132","258","61","84","87"],"bracket":{"seeds":[{"team_id":"194","team_name":"Ohio State Buckeyes","seed":1,"fpi":38.53},{"team_id":"84","team_name":"Indiana Hoosiers","seed":2,"fpi":36.28},{"team_id":"87","team_name":"Notre Dame Fighting Irish","seed":3,"fpi":31.73},{"team_id":"103","team_name":"Boston College Eagles","seed":4,"fpi":27.68},{"team_id":"2","team_name":"Auburn Tigers","seed":5,"fpi":25.93},{"team_id":"61","team_name":"Georgia Bulldogs","seed":6,"fpi":21.71},{"team_id":"213","team_name":"Penn State Nittany Lions","seed":7,"fpi":20.8},{"team_id":"201","team_name":"Oklahoma Sooners","seed":8,"fpi":20.15},{"team_id":"189","team_name":"Bowling Green Falcons","seed":9,"fpi":13.92},{"team_id":"258","team_name":"Virginia Cavaliers","seed":10,"fpi":12.76},{"team_id":"2132","team_name":"Cincinnati Bearcats","seed":11,"fpi":11.8},{"team_id":"2116","team_name":"UCF Knights","seed":12,"fpi":10.18}],"r1":[[5,12],[6,11],[7,10],[8,9]],"title_odds_by_team_id":{"194":38.36,"84":28.26,"87":18.24,"103":8.07,"2":4.13,"61":1.42,"213":0.74,"201":0.59,"189":0.07,"258":0.05,"2132":0.05,"2116":0.03}},"conf_champions":{"ACC":"258","American":"235","Big 12":"2132","Big Ten":"194","CUSA":"98","MAC":"2649","Mountain West":"2449","Pac-12":"265","SEC":"2","Sun Belt":"295"},"conf_finalists":{"ACC":["103","258"],"American":["2426","235"],"Big 12":["2132","252"],"Big Ten":["84","194"],"CUSA":["98","338"],"MAC":["189","2649"],"Mountain West":["2449","2459"],"Pac-12":["68","265"],"SEC":["61","2"],"Sun Belt":["295","2032"]}}