{"field":["164","194","213","2294","2390","251","2579","61","68","84","87","9"],"bracket":{"seeds":[{"team_id":"194","team_name":"Ohio State Buckeyes","seed":1,"fpi":36.2,"wins":12,"losses":1,"record":"12-1"},{"team_id":"213","team_name":"Penn State Nittany Lions","seed":2,"fpi":34.34,"wins":12,"losses":1,"record":"12-1"},{"team_id":"61","team_name":"Georgia Bulldogs","seed":3,"fpi":32.45,"wins":12,"losses":1,"record":"12-1"},{"team_id":"84","team_name":"Indiana Hoosiers","seed":4,"fpi":28.96,"wins":11,"losses":1,"record":"11-1"},{"team_id":"9","team_name":"Arizona State Sun Devils","seed":5,"fpi":22.24,"wins":12,"losses":1,"record":"12-1"},{"team_id":"87","team_name":"Notre Dame Fighting Irish","seed":6,"fpi":20.01,"wins":11,"losses":1,"record":"11-1"},{"team_id":"2579","team_name":"South Carolina Gamecocks","seed":7,"fpi":18.34,"wins":10,"losses":3,"record":"10-3"},{"team_id":"2294","team_name":"Iowa Hawkeyes","seed":8,"fpi":17.28,"wins":11,"losses":1,"record":"11-1"},{"team_id":"251","team_name":"Texas Longhorns","seed":9,"fpi":16.84,"wins":8,"losses":4,"record":"8-4"},{"team_id":"68","team_name":"Boise State Broncos","seed":10,"fpi":14.04,"wins":11,"losses":1,"record":"11-1"},{"team_id":"2390","team_name":"Miami Hurricanes","seed":11,"fpi":13.4,"wins":10,"losses":3,"record":"10-3"},{"team_id":"164","team_name":"Rutgers Scarlet Knights","seed":12,"fpi":12.53,"wins":10,"losses":2,"record":"10-2"}],"r1":[[5,12],[6,11],[7,10],[8,9]],"title_odds_by_team_id":{"194":33.89,"213":26.35,"61":23.05,"84":12.41,"9":1.88,"87":1.01,"2579":0.5,"2294":0.32,"251":0.28,"68":0.12,"2390":0.11,"164":0.08}},"conf_champions":{"ACC":"2390","American":"2426","Big 12":"9","Big Ten":"194","CUSA":"2393","MAC":"193","Mountain West":"62","Pac-12":"68","SEC":"61","Sun Belt":"309"},"conf_finalists":{"ACC":["97","2390"],"American":["2655","2426"],"Big 12":["9","2641"],"Big Ten":["213","194"],"CUSA":["166","2393"],"MAC":["193","2084"],"Mountain West":["62","2440"],"Pac-12":["68","326"],"SEC":["61","2579"],"Sun Belt":["256","309"]}}