{"field":["130","2294","2306","235","2390","2483","254","2579","277","61","84","87"],"bracket":{"seeds":[{"team_id":"130","team_name":"Michigan Wolverines","seed":1,"fpi":35.75},{"team_id":"2483","team_name":"Oregon Ducks","seed":2,"fpi":25.82},{"team_id":"2390","team_name":"Miami Hurricanes","seed":3,"fpi":22.75},{"team_id":"87","team_name":"Notre Dame Fighting Irish","seed":4,"fpi":22.18},{"team_id":"2306","team_name":"Kansas State Wildcats","seed":5,"fpi":21.36},{"team_id":"254","team_name":"Utah Utes","seed":6,"fpi":20.77},{"team_id":"2294","team_name":"Iowa Hawkeyes","seed":7,"fpi":20.27},{"team_id":"277","team_name":"West Virginia Mountaineers","seed":8,"fpi":17.23},{"team_id":"84","team_name":"Indiana Hoosiers","seed":9,"fpi":16.77},{"team_id":"235","team_name":"Memphis Tigers","seed":10,"fpi":16.18},{"team_id":"61","team_name":"Georgia Bulldogs","seed":11,"fpi":15.3},{"team_id":"2579","team_name":"South Carolina Gamecocks","seed":12,"fpi":10.38}],"r1":[[5,12],[6,11],[7,10],[8,9]],"title_odds_by_team_id":{"130":53.4,"2483":13.3,"2390":9.79,"87":8.94,"2306":5.04,"254":3.75,"2294":2.35,"277":0.96,"84":0.83,"235":0.7,"61":0.77,"2579":0.18}},"conf_champions":{"ACC":"2390","American":"235","Big 12":"254","Big Ten":"130","CUSA":"2335","MAC":"195","Mountain West":"2439","Pac-12":"265","SEC":"2579","Sun Belt":"295"},"conf_finalists":{"ACC":["2390","228"],"American":["235","2655"],"Big 12":["2306","254"],"Big Ten":["130","2483"],"CUSA":["2335","48"],"MAC":["189","195"],"Mountain West":["2439","2449"],"Pac-12":["265","204"],"SEC":["2579","99"],"Sun Belt":["295","2653"]}}