{"field":["158","194","201","2641","30","38","66","68","8","84","87","97"],"bracket":{"seeds":[{"team_id":"84","team_name":"Indiana Hoosiers","seed":1,"fpi":36.77},{"team_id":"87","team_name":"Notre Dame Fighting Irish","seed":2,"fpi":31.89},{"team_id":"97","team_name":"Louisville Cardinals","seed":3,"fpi":27.96},{"team_id":"158","team_name":"Nebraska Cornhuskers","seed":4,"fpi":26.77},{"team_id":"8","team_name":"Arkansas Razorbacks","seed":5,"fpi":23.83},{"team_id":"194","team_name":"Ohio State Buckeyes","seed":6,"fpi":23.47},{"team_id":"201","team_name":"Oklahoma Sooners","seed":7,"fpi":23.28},{"team_id":"2641","team_name":"Texas Tech Red Raiders","seed":8,"fpi":20.63},{"team_id":"68","team_name":"Boise State Broncos","seed":9,"fpi":15.87},{"team_id":"66","team_name":"Iowa State Cyclones","seed":10,"fpi":15.41},{"team_id":"38","team_name":"Colorado Buffaloes","seed":11,"fpi":10.18},{"team_id":"30","team_name":"USC Trojans","seed":12,"fpi":5.75}],"r1":[[5,12],[6,11],[7,10],[8,9]],"title_odds_by_team_id":{"84":42.4,"87":20.81,"97":13.61,"158":10.85,"8":4.58,"194":3.81,"201":2.3,"2641":1.14,"68":0.24,"66":0.19,"38":0.05,"30":0.01}},"conf_champions":{"ACC":"97","American":"151","Big 12":"2641","Big Ten":"84","CUSA":"166","MAC":"2649","Mountain West":"2005","Pac-12":"68","SEC":"8","Sun Belt":"256"},"conf_finalists":{"ACC":["2567","97"],"American":["151","2426"],"Big 12":["66","2641"],"Big Ten":["84","30"],"CUSA":["166","55"],"MAC":["2649","2309"],"Mountain West":["2005","62"],"Pac-12":["68","265"],"SEC":["201","8"],"Sun Belt":["295","256"]}}