{"field":["130","142","167","2116","228","2294","2305","2390","251","2641","333","97"],"bracket":{"seeds":[{"team_id":"130","team_name":"Michigan Wolverines","seed":1,"fpi":34.45},{"team_id":"97","team_name":"Louisville Cardinals","seed":2,"fpi":29.94},{"team_id":"333","team_name":"Alabama Crimson Tide","seed":3,"fpi":29.8},{"team_id":"2641","team_name":"Texas Tech Red Raiders","seed":4,"fpi":28.4},{"team_id":"167","team_name":"New Mexico Lobos","seed":5,"fpi":26.94},{"team_id":"2305","team_name":"Kansas Jayhawks","seed":6,"fpi":26.82},{"team_id":"251","team_name":"Texas Longhorns","seed":7,"fpi":23.76},{"team_id":"2116","team_name":"UCF Knights","seed":8,"fpi":22.06},{"team_id":"142","team_name":"Missouri Tigers","seed":9,"fpi":20.71},{"team_id":"2294","team_name":"Iowa Hawkeyes","seed":10,"fpi":18.94},{"team_id":"2390","team_name":"Miami Hurricanes","seed":11,"fpi":13.87},{"team_id":"228","team_name":"Clemson Tigers","seed":12,"fpi":10.92}],"r1":[[5,12],[6,11],[7,10],[8,9]],"title_odds_by_team_id":{"130":33.72,"97":17.01,"333":16.49,"2641":12.95,"167":7.26,"2305":6.48,"251":2.71,"2116":1.56,"142":1.03,"2294":0.63,"2390":0.12,"228":0.05}},"conf_champions":{"ACC":"228","American":"2655","Big 12":"2641","Big Ten":"130","CUSA":"55","MAC":"195","Mountain West":"167","Pac-12":"326","SEC":"251","Sun Belt":"256"},"conf_finalists":{"ACC":["97","228"],"American":["235","2655"],"Big 12":["2641","2305"],"Big Ten":["130","2294"],"CUSA":["55","48"],"MAC":["195","2649"],"Mountain West":["167","2449"],"Pac-12":["326","36"],"SEC":["333","251"],"Sun Belt":["256","2032"]}}