{"field":["2294","2390","245","2483","251","254","349","38","61","84","87","97"],"bracket":{"seeds":[{"team_id":"61","team_name":"Georgia Bulldogs","seed":1,"fpi":28.57},{"team_id":"2483","team_name":"Oregon Ducks","seed":2,"fpi":24.62},{"team_id":"97","team_name":"Louisville Cardinals","seed":3,"fpi":23.67},{"team_id":"84","team_name":"Indiana Hoosiers","seed":4,"fpi":22.81},{"team_id":"245","team_name":"Texas A&M Aggies","seed":5,"fpi":22.65},{"team_id":"87","team_name":"Notre Dame Fighting Irish","seed":6,"fpi":22.52},{"team_id":"254","team_name":"Utah Utes","seed":7,"fpi":22.21},{"team_id":"251","team_name":"Texas Longhorns","seed":8,"fpi":19.28},{"team_id":"2390","team_name":"Miami Hurricanes","seed":9,"fpi":17.48},{"team_id":"2294","team_name":"Iowa Hawkeyes","seed":10,"fpi":16.82},{"team_id":"349","team_name":"Army Black Knights","seed":11,"fpi":8.12},{"team_id":"38","team_name":"Colorado Buffaloes","seed":12,"fpi":7.47}],"r1":[[5,12],[6,11],[7,10],[8,9]],"title_odds_by_team_id":{"61":29.62,"2483":15.45,"97":14.37,"84":12.36,"245":8.81,"87":8.33,"254":5.54,"251":2.6,"2390":1.53,"2294":1.21,"349":0.11,"38":0.09}},"conf_champions":{"ACC":"2390","American":"349","Big 12":"254","Big Ten":"84","CUSA":"2335","MAC":"2199","Mountain West":"2439","Pac-12":"21","SEC":"61","Sun Belt":"256"},"conf_finalists":{"ACC":["97","2390"],"American":["349","2426"],"Big 12":["38","254"],"Big Ten":["84","2294"],"CUSA":["166","2335"],"MAC":["2117","2199"],"Mountain West":["2449","2439"],"Pac-12":["68","21"],"SEC":["61","245"],"Sun Belt":["256","309"]}}