{"field":["130","201","2116","245","2483","252","259","2636","61","84","87","99"],"bracket":{"seeds":[{"team_id":"2483","team_name":"Oregon Ducks","seed":1,"fpi":34.0,"wins":13,"losses":0,"record":"13-0"},{"team_id":"87","team_name":"Notre Dame Fighting Irish","seed":2,"fpi":33.55,"wins":12,"losses":0,"record":"12-0"},{"team_id":"84","team_name":"Indiana Hoosiers","seed":3,"fpi":28.3,"wins":10,"losses":2,"record":"10-2"},{"team_id":"201","team_name":"Oklahoma Sooners","seed":4,"fpi":24.79,"wins":13,"losses":0,"record":"13-0"},{"team_id":"245","team_name":"Texas A&M Aggies","seed":5,"fpi":24.35,"wins":11,"losses":2,"record":"11-2"},{"team_id":"99","team_name":"LSU Tigers","seed":6,"fpi":21.36,"wins":10,"losses":2,"record":"10-2"},{"team_id":"130","team_name":"Michigan Wolverines","seed":7,"fpi":20.18,"wins":10,"losses":3,"record":"10-3"},{"team_id":"61","team_name":"Georgia Bulldogs","seed":8,"fpi":19.08,"wins":11,"losses":1,"record":"11-1"},{"team_id":"2116","team_name":"UCF Knights","seed":9,"fpi":17.31,"wins":12,"losses":1,"record":"12-1"},{"team_id":"2636","team_name":"UTSA Roadrunners","seed":10,"fpi":16.71,"wins":13,"losses":0,"record":"13-0"},{"team_id":"259","team_name":"Virginia Tech Hokies","seed":11,"fpi":16.5,"wins":13,"losses":0,"record":"13-0"},{"team_id":"252","team_name":"BYU Cougars","seed":12,"fpi":15.77,"wins":10,"losses":3,"record":"10-3"}],"r1":[[5,12],[6,11],[7,10],[8,9]],"title_odds_by_team_id":{"2483":32.8,"87":30.53,"84":16.95,"201":8.65,"245":4.94,"99":2.29,"130":1.18,"61":0.87,"2116":0.49,"2636":0.39,"259":0.51,"252":0.39}},"conf_champions":{"ACC":"259","American":"2636","Big 12":"2116","Big Ten":"2483","CUSA":"2335","MAC":"2649","Mountain West":"167","Pac-12":"204","SEC":"201","Sun Belt":"295"},"conf_finalists":{"ACC":["259","97"],"American":["2636","235"],"Big 12":["252","2116"],"Big Ten":["2483","130"],"CUSA":["2335","166"],"MAC":["2649","189"],"Mountain West":["2005","167"],"Pac-12":["68","204"],"SEC":["201","245"],"Sun Belt":["295","2032"]}}