{"field":["12","130","154","158","228","2483","251","295","30","333","61","87"],"bracket":{"seeds":[{"team_id":"2483","team_name":"Oregon Ducks","seed":1,"fpi":36.87},{"team_id":"61","team_name":"Georgia Bulldogs","seed":2,"fpi":36.72},{"team_id":"333","team_name":"Alabama Crimson Tide","seed":3,"fpi":36.46},{"team_id":"251","team_name":"Texas Longhorns","seed":4,"fpi":32.89},{"team_id":"130","team_name":"Michigan Wolverines","seed":5,"fpi":22.83},{"team_id":"12","team_name":"Arizona Wildcats","seed":6,"fpi":21.48},{"team_id":"158","team_name":"Nebraska Cornhuskers","seed":7,"fpi":21.19},{"team_id":"87","team_name":"Notre Dame Fighting Irish","seed":8,"fpi":19.66},{"team_id":"295","team_name":"Old Dominion Monarchs","seed":9,"fpi":16.79},{"team_id":"228","team_name":"Clemson Tigers","seed":10,"fpi":16.69},{"team_id":"154","team_name":"Wake Forest Demon Deacons","seed":11,"fpi":14.25},{"team_id":"30","team_name":"USC Trojans","seed":12,"fpi":13.92}],"r1":[[5,12],[6,11],[7,10],[8,9]],"title_odds_by_team_id":{"2483":27.45,"61":26.32,"333":27.68,"251":15.42,"130":1.09,"12":0.74,"158":0.56,"87":0.37,"295":0.14,"228":0.12,"154":0.06,"30":0.06}},"conf_champions":{"ACC":"228","American":"2655","Big 12":"12","Big Ten":"2483","CUSA":"338","MAC":"193","Mountain West":"2005","Pac-12":"328","SEC":"61","Sun Belt":"295"},"conf_finalists":{"ACC":["228","2567"],"American":["2636","2655"],"Big 12":["12","66"],"Big Ten":["2483","158"],"CUSA":["338","2393"],"MAC":["2649","193"],"Mountain West":["2449","2005"],"Pac-12":["68","328"],"SEC":["333","61"],"Sun Belt":["295","6"]}}